unittest_ft/__init__.py
unittest_ft/__main__.py
unittest_ft/__version__.py
unittest_ft/cli.py
unittest_ft/core.py
unittest_ft/tests/__init__.py
unittest_ft/tests/__main__.py
unittest_ft/tests/smoke.py
unittest_ft-0.5.dist-info/entry_points.txt
unittest_ft-0.5.dist-info/licenses/LICENSE
unittest_ft-0.5.dist-info/WHEEL
unittest_ft-0.5.dist-info/METADATA
unittest_ft-0.5.dist-info/RECORD
