Metadata-Version: 2.4
Name: unittest-ft
Version: 0.5
Summary: Run tests in parallel with free threading
Author-email: Amethyst Reese <amethyst@n7.gg>
Requires-Python: >=3.8
Classifier: Development Status :: 4 - Beta
Classifier: License :: OSI Approved :: MIT License
Classifier: Programming Language :: Python :: 3
Classifier: Topic :: Software Development :: Testing
License-File: LICENSE
Requires-Dist: click >= 8
Requires-Dist: typing-extensions >= 4.8.0
Requires-Dist: attribution>=1.8 ; extra == "dev"
Requires-Dist: black==25.1.0 ; extra == "dev"
Requires-Dist: build>=1.2 ; extra == "dev"
Requires-Dist: flake8==7.2.0 ; extra == "dev"
Requires-Dist: mypy==1.16.0 ; extra == "dev"
Requires-Dist: ufmt==2.8.0 ; extra == "dev"
Requires-Dist: usort==1.0.8.post1 ; extra == "dev"
Project-URL: Home, https://github.com/amyreese/unittest-ft
Provides-Extra: dev
